{
  "Location": [
    {
      "id": 1,
      "LOC_CD": "ATLNZ",
      "LOC_NAME": "LINZ",
      "CNTRY_CODE": "AT",
      "STATE": "OB"
    },
    {
      "id": 2,
      "LOC_CD": "CHBSL",
      "LOC_NAME": "BASEL",
      "CNTRY_CODE": "CH",
      "STATE": "BS"
    },
    {
      "id": 3,
      "LOC_CD": "CHFKD",
      "LOC_NAME": "FRENKENDORF",
      "CNTRY_CODE": "CH",
      "STATE": "BL"
    },
    {
      "id": 4,
      "LOC_CD": "AAAA",
      "LOC_NAME": "CCCC",
      "CNTRY_CODE": "KK",
      "STATE": "LL"
    }
  ]
}